juniper/__init__.py
juniper/actions.py
juniper/cli.py
juniper/constants.py
juniper/io.py
juniper/manifest.py
juniper/artifacts/build_layer.sh
juniper/artifacts/compose-template.yml
juniper/artifacts/package.sh
tests/__init__.py
tests/test_actions.py
tests/test_build_with_overrides.py
tests/test_cli.py
tests/test_manifest.py
juniper-0.5.5.dist-info/AUTHORS
juniper-0.5.5.dist-info/LICENSE
juniper-0.5.5.dist-info/METADATA
juniper-0.5.5.dist-info/WHEEL
juniper-0.5.5.dist-info/entry_points.txt
juniper-0.5.5.dist-info/top_level.txt
juniper-0.5.5.dist-info/RECORD
