Metadata-Version: 2.1
Name: juniper
Version: 0.5.5
Summary: Tool to streamline the build of python lambda functions.
Home-page: UNKNOWN
Author: EAB Tech
Author-email: eabtech@eab.com
License: Apache Software License
Project-URL: Documentation, https://eabglobal.github.io/juniper/
Project-URL: Code, https://github.com/eabglobal/juniper
Project-URL: Issue tracker, https://github.com/eabglobal/juniper/issues
Platform: UNKNOWN
Classifier: Environment :: Web Environment
Classifier: Intended Audience :: Developers
Classifier: License :: OSI Approved :: Apache Software License
Classifier: Operating System :: OS Independent
Classifier: Programming Language :: Python
Classifier: Programming Language :: Python :: 3.6
Classifier: Programming Language :: Python :: 3.7
Classifier: Topic :: Software Development :: Libraries :: Python Modules
Classifier: Topic :: Software Development :: Build Tools
Requires-Python: >=3.6
Requires-Dist: click (>=5.1)
Requires-Dist: click-log
Requires-Dist: PyYAML (<=5.3,>=4.3)
Requires-Dist: Jinja2 (>=2.10)
Requires-Dist: docker[ssh] (>=5)
Requires-Dist: docker-compose (>=1.29)
